MANIFEST.in
README.txt
setup.py
docs/HISTORY.txt
iuem/__init__.py
iuem.photorepository.egg-info/PKG-INFO
iuem.photorepository.egg-info/SOURCES.txt
iuem.photorepository.egg-info/dependency_links.txt
iuem.photorepository.egg-info/entry_points.txt
iuem.photorepository.egg-info/namespace_packages.txt
iuem.photorepository.egg-info/not-zip-safe
iuem.photorepository.egg-info/requires.txt
iuem.photorepository.egg-info/top_level.txt
iuem/photorepository/__init__.py
iuem/photorepository/configure.zcml
iuem/photorepository/controlpanel.py
iuem/photorepository/extender.py
iuem/photorepository/interfaces.py
iuem/photorepository/manageVocabulary.py
iuem/photorepository/rebuild_i18n.sh
iuem/photorepository/subscribers.py
iuem/photorepository/validators.py
iuem/photorepository/browser/__init__.py
iuem/photorepository/browser/configure.zcml
iuem/photorepository/browser/debugSet.pt
iuem/photorepository/browser/debugSet.py
iuem/photorepository/browser/fillInVocabularies.pt
iuem/photorepository/browser/fillInVocabularies.py
iuem/photorepository/browser/fullImageView.pt
iuem/photorepository/browser/fullimageview.py
iuem/photorepository/browser/imdebug.py
iuem/photorepository/browser/interfaces.py
iuem/photorepository/browser/manageMetadataFormView.pt
iuem/photorepository/browser/manageMetadata_form.py
iuem/photorepository/browser/metadataConfirm.pt
iuem/photorepository/browser/metadataConfirm.py
iuem/photorepository/browser/repoFolderContents.pt
iuem/photorepository/browser/repoFolderContents.py
iuem/photorepository/browser/repoFolderView.py
iuem/photorepository/browser/repoImageView.py
iuem/photorepository/browser/repoTable.pt
iuem/photorepository/browser/repofolderalbumview.pt
iuem/photorepository/browser/repoimageview.pt
iuem/photorepository/browser/requestAlbum.pt
iuem/photorepository/browser/requestAlbum.py
iuem/photorepository/browser/requestAlbumFormResult.pt
iuem/photorepository/browser/requestImage.pt
iuem/photorepository/browser/requestImage.py
iuem/photorepository/browser/requestImageFormResult.pt
iuem/photorepository/browser/watermarks.py
iuem/photorepository/locales/README.txt
iuem/photorepository/locales/iuem.photorepository.pot
iuem/photorepository/locales/en/LC_MESSAGES/iuem.photorepository.mo
iuem/photorepository/locales/en/LC_MESSAGES/iuem.photorepository.po
