Metadata-Version: 1.1
Name: iuem.photorepository
Version: 1.0b2
Summary: Addon for Plone
Home-page: https://github.com/erichardy/iuem.photorepository
Author: Eric Hardy
Author-email: Eric.Hardy@univ-brest.fr
License: GPL
Keywords: image repository
Platform: UNKNOWN
Classifier: Programming Language :: Python
Classifier: Framework :: Plone
Classifier: Framework :: Plone :: 4.1
Classifier: Framework :: Plone :: 4.2
